PyMemory/PyMemory.dll
PyMemory/__init__.py
PyMemory-0.0.7.dist-info/LICENSE
PyMemory-0.0.7.dist-info/METADATA
PyMemory-0.0.7.dist-info/WHEEL
PyMemory-0.0.7.dist-info/top_level.txt
PyMemory-0.0.7.dist-info/RECORD
