Metadata-Version: 2.1
Name: PyMemory
Version: 0.0.7
Summary: Happy using PyMemory to read and write to computer memory.
Home-page: https://github.com/PyMario/PyMemory
Author: PyMario
Author-email: rumu3f@gmail.com
License: UNKNOWN
Platform: UNKNOWN
Classifier: Programming Language :: Python :: 3
Classifier: License :: OSI Approved :: MIT License
Classifier: Operating System :: Microsoft :: Windows :: Windows 10
Requires-Python: >=3.6
